MANIFEST.in
README
setup.py
pinax_theme_jquerymobile/__init__.py
pinax_theme_jquerymobile.egg-info/PKG-INFO
pinax_theme_jquerymobile.egg-info/SOURCES.txt
pinax_theme_jquerymobile.egg-info/dependency_links.txt
pinax_theme_jquerymobile.egg-info/not-zip-safe
pinax_theme_jquerymobile.egg-info/top_level.txt
pinax_theme_jquerymobile/static/css/jquery.mobile-1.0b3.css
pinax_theme_jquerymobile/static/css/jquery.mobile-1.0b3.min.css
pinax_theme_jquerymobile/static/css/images/ajax-loader.png
pinax_theme_jquerymobile/static/css/images/icon-search-black.png
pinax_theme_jquerymobile/static/css/images/icons-18-black.png
pinax_theme_jquerymobile/static/css/images/icons-18-white.png
pinax_theme_jquerymobile/static/css/images/icons-36-black.png
pinax_theme_jquerymobile/static/css/images/icons-36-white.png
pinax_theme_jquerymobile/static/js/jquery-1.6.3.min.js
pinax_theme_jquerymobile/static/js/jquery.mobile-1.0b3.js
pinax_theme_jquerymobile/static/js/jquery.mobile-1.0b3.min.js
pinax_theme_jquerymobile/templates/navbar.html
pinax_theme_jquerymobile/templates/theme_base.html
pinax_theme_jquerymobile/templates/account/base.html
pinax_theme_jquerymobile/templates/account/email.html
pinax_theme_jquerymobile/templates/account/language_change.html
pinax_theme_jquerymobile/templates/account/login.html
pinax_theme_jquerymobile/templates/account/logout.html
pinax_theme_jquerymobile/templates/account/password_change.html
pinax_theme_jquerymobile/templates/account/password_delete.html
pinax_theme_jquerymobile/templates/account/password_delete_done.html
pinax_theme_jquerymobile/templates/account/password_reset.html
pinax_theme_jquerymobile/templates/account/password_reset_done.html
pinax_theme_jquerymobile/templates/account/password_reset_from_key.html
pinax_theme_jquerymobile/templates/account/password_reset_key_message.txt
pinax_theme_jquerymobile/templates/account/password_reset_message.txt
pinax_theme_jquerymobile/templates/account/password_set.html
pinax_theme_jquerymobile/templates/account/signup.html
pinax_theme_jquerymobile/templates/account/timezone_change.html
pinax_theme_jquerymobile/templates/account/verification_sent.html
pinax_theme_jquerymobile/templates/biblion/_comments.html
