Metadata-Version: 1.0
Name: pinax-theme-jquerymobile
Version: 0.2.4
Summary: a theme for Pinax based on jQuery Mobile
Home-page: http://github.com/MechanisM/pinax-theme-jquerymobile
Author: Eugene MechanisM
Author-email: contact@mechanism.name
License: MIT
Platform: UNKNOWN
Classifier: Development Status :: 3 - Alpha
Classifier: Environment :: Web Environment
Classifier: Intended Audience :: Developers
Classifier: License :: OSI Approved :: BSD License
Classifier: Operating System :: OS Independent
Classifier: Programming Language :: Python
Classifier: Framework :: Django
